anesthetic/__init__.py
anesthetic/_code_utils.py
anesthetic/_format.py
anesthetic/_version.py
anesthetic/boundary.py
anesthetic/convert.py
anesthetic/kde.py
anesthetic/labelled_pandas.py
anesthetic/plot.py
anesthetic/samples.py
anesthetic/scripts.py
anesthetic/tension.py
anesthetic/testing.py
anesthetic/utils.py
anesthetic/weighted_labelled_pandas.py
anesthetic/weighted_pandas.py
anesthetic/examples/__init__.py
anesthetic/examples/_matplotlib_agg.py
anesthetic/examples/perfect_ns.py
anesthetic/examples/utils.py
anesthetic/gui/__init__.py
anesthetic/gui/plot.py
anesthetic/gui/widgets.py
anesthetic/plotting/__init__.py
anesthetic/plotting/_core.py
anesthetic/plotting/_matplotlib/__init__.py
anesthetic/plotting/_matplotlib/boxplot.py
anesthetic/plotting/_matplotlib/core.py
anesthetic/plotting/_matplotlib/hist.py
anesthetic/plotting/_matplotlib/misc.py
anesthetic/read/__init__.py
anesthetic/read/chain.py
anesthetic/read/cobaya.py
anesthetic/read/csv.py
anesthetic/read/getdist.py
anesthetic/read/hdf.py
anesthetic/read/multinest.py
anesthetic/read/nestedfit.py
anesthetic/read/polychord.py
anesthetic/read/ultranest.py
anesthetic-2.11.3.dist-info/licenses/LICENSE
anesthetic-2.11.3.dist-info/METADATA
anesthetic-2.11.3.dist-info/WHEEL
anesthetic-2.11.3.dist-info/entry_points.txt
anesthetic-2.11.3.dist-info/top_level.txt
anesthetic-2.11.3.dist-info/RECORD
