Metadata-Version: 2.4
Name: anesthetic
Version: 2.11.3
Summary: nested sampling post-processing
Author-email: Will Handley <williamjameshandley@gmail.com>, Lukas Hergt <lthergt@phas.ubc.ca>, Adam Ormondroyd <ano23@cam.ac.uk>, Harry Bevins <htjb2@cam.ac.uk>, Johannes Buchner <jbuchner@mpe.mpg.de>, Ethan Carragher <ethan.carragher@adelaide.edu.au>, Andrew Fowlie <andrew.j.fowlie@googlemail.com>, Thomas Gessey-Jones <tg400@cam.ac.uk>, Stefan Heimersheim <sh2061@ast.cam.ac.uk>, Pablo Lemos <plemos91@gmail.com>, Toby Lovick <tcl44@cam.ac.uk>, Deborah Odunuyi <debbieodunuyi@gmail.com>, Aleksandr
Maintainer-email: Will Handley <williamjameshandley@gmail.com>, Lukas Hergt <lthergt@phas.ubc.ca>
License: MIT License
Project-URL: Homepage, https://github.com/handley-lab/anesthetic
Project-URL: Bug Tracker, https://github.com/handley-lab/anesthetic/issues
Project-URL: Documentation, https://anesthetic.readthedocs.io/en/latest/
Project-URL: JOSS paper, https://joss.theoj.org/papers/10.21105/joss.01414
Classifier: Programming Language :: Python :: 3
Classifier: License :: OSI Approved :: MIT License
Classifier: Operating System :: OS Independent
Classifier: Development Status :: 5 - Production/Stable
Classifier: Intended Audience :: Developers
Classifier: Intended Audience :: Science/Research
Classifier: Natural Language :: English
Classifier: Topic :: Scientific/Engineering
Classifier: Topic :: Scientific/Engineering :: Astronomy
Classifier: Topic :: Scientific/Engineering :: Physics
Classifier: Topic :: Scientific/Engineering :: Visualization
Classifier: Topic :: Scientific/Engineering :: Information Analysis
Classifier: Topic :: Scientific/Engineering :: Mathematics
Requires-Python: >=3.8
License-File: LICENSE
Requires-Dist: scipy<2.0.0
Requires-Dist: numpy<3.0.0,>=1.26.0
Requires-Dist: pandas<2.4.0,>=2.2.0
Requires-Dist: matplotlib<3.11.0,>=3.6.1
Provides-Extra: docs
Requires-Dist: sphinx>=4.2.0; extra == "docs"
Requires-Dist: sphinx_rtd_theme>=1.2.2; extra == "docs"
Requires-Dist: sphinx-copybutton; extra == "docs"
Requires-Dist: sphinx-autodoc-typehints; extra == "docs"
Requires-Dist: numpydoc; extra == "docs"
Provides-Extra: test
Requires-Dist: pytest; extra == "test"
Requires-Dist: pytest-cov; extra == "test"
Requires-Dist: flake8; extra == "test"
Requires-Dist: pydocstyle; extra == "test"
Requires-Dist: packaging; extra == "test"
Requires-Dist: pre-commit; extra == "test"
Provides-Extra: ultranest
Requires-Dist: h5py; extra == "ultranest"
Provides-Extra: astropy
Requires-Dist: astropy; extra == "astropy"
Provides-Extra: fastkde
Requires-Dist: fastkde; extra == "fastkde"
Provides-Extra: getdist
Requires-Dist: getdist; extra == "getdist"
Provides-Extra: hdf5
Requires-Dist: tables==3.8.0; extra == "hdf5"
Provides-Extra: all
Requires-Dist: h5py; extra == "all"
Requires-Dist: astropy; extra == "all"
Requires-Dist: fastkde; extra == "all"
Requires-Dist: getdist; extra == "all"
Requires-Dist: tables; extra == "all"
Dynamic: license-file
